{"id":"26d18921-9341-4ec0-815f-648416491a91","first_name":"Jessica","last_name":"Boggs","email_address":"jessica.boggs@bishopr.co.uk","dfe_uuid":"0b8f759c-df6b-4150-af22-6c62373231da","created_at":"2020-02-07 14:27:51 +0000","updated_at":"2020-02-07 14:27:51 +0000","send_notifications":true,"providers":[{"code":"L79","name":"Loughborough University","permissions":{"manage_users":true,"view_safeguarding_information":false,"make_decisions":true,"manage_organisations":true,"view_diversity_information":false}}]}