{"id":"522cd6bc-0617-4316-9252-4eb0d386a39f","first_name":"Kyle","last_name":"Howlett","email_address":"kyle.howlett@myoakthorpe.net","dfe_uuid":"aa729755-cd89-426f-8f97-86d4404c13ef","created_at":"2020-09-11 14:30:10 +0100","updated_at":"2020-09-11 14:30:10 +0100","send_notifications":true,"providers":[{"code":"151","name":"Oakthorpe Primary School","permissions":{"manage_users":true,"view_safeguarding_information":true,"make_decisions":true,"manage_organisations":true,"view_diversity_information":true}}]}