{"id":"8f8b8e09-1c2f-43c3-a3d2-f72e9810ca96","first_name":"Otto","last_name":"Barnes","email_address":"otto.barnes@beds.ac.uk","dfe_uuid":"4cc7cf97-cd2d-4a89-aee7-986e259c5556","created_at":"2020-10-13 12:25:10 +0100","updated_at":"2021-03-25 09:17:32 +0000","last_signed_in_at":"2021-03-25 09:17:32 +0000","send_notifications":true,"providers":[{"code":"D40","name":"Devon Primary SCITT","permissions":{"manage_users":true,"view_safeguarding_information":true,"make_decisions":true,"manage_organisations":true,"view_diversity_information":true}}]}