{"id":"e886ec59-03ff-451d-ada9-79fdeba115b0","first_name":"Peter","last_name":"Gibson","email_address":"peter.gibson@redkitealliance.co.uk","dfe_uuid":"203495d1-3fd0-4d6a-aad5-661c895fd907","created_at":"2020-09-30 10:09:11 +0100","updated_at":"2021-02-09 11:30:07 +0000","last_signed_in_at":"2021-02-09 11:30:07 +0000","send_notifications":true,"providers":[{"code":"1EX","name":"Greenwood Academies Trust","permissions":{"manage_users":true,"view_safeguarding_information":true,"make_decisions":true,"manage_organisations":true,"view_diversity_information":true}}]}